rlooper_sim_python/Snakefile
rlooper_sim_python/__init__.py
rlooper_sim_python/cli.py
rlooper_sim_python/dag_fallback.py
rlooper_sim_python/gene.py
rlooper_sim_python/grapher.py
rlooper_sim_python/main.py
rlooper_sim_python/model.py
rlooper_sim_python/simulation.py
rlooper_sim_python/structure.py
rlooper_sim_python/version.py
rlooper_sim_python/workflow.py
rlooper_sim_python/data/energy.csv
rlooper_sim_python/examples/example.fasta
rlooper_sim_python/examples/example_short.fasta
rlooper_sim_python-1.1.3.dist-info/licenses/LICENSE
rlooper_sim_python-1.1.3.dist-info/METADATA
rlooper_sim_python-1.1.3.dist-info/WHEEL
rlooper_sim_python-1.1.3.dist-info/entry_points.txt
rlooper_sim_python-1.1.3.dist-info/top_level.txt
rlooper_sim_python-1.1.3.dist-info/RECORD
