Metadata-Version: 2.4
Name: rlooper-sim-python
Version: 1.1.3
Summary: Rlooper with R-loop Peak Simulation - Python Implementation
Author-email: srhartono <srhartono@ucdavis.edu>
Project-URL: Homepage, https://github.com/srhartono/rlooper_sim_python
Project-URL: Repository, https://github.com/srhartono/rlooper_sim_python
Project-URL: Issues, https://github.com/srhartono/rlooper_sim_python/issues
Project-URL: Documentation, https://github.com/srhartono/rlooper_sim_python#readme
Keywords: rlooper,simulation,bioinformatics,snakemake,genomics
Classifier: Development Status :: 5 - Production/Stable
Classifier: Intended Audience :: Science/Research
Classifier: License :: OSI Approved :: MIT License
Classifier: Operating System :: OS Independent
Classifier: Programming Language :: Python :: 3
Classifier: Programming Language :: Python :: 3.8
Classifier: Programming Language :: Python :: 3.9
Classifier: Programming Language :: Python :: 3.10
Classifier: Programming Language :: Python :: 3.11
Classifier: Programming Language :: Python :: 3.12
Classifier: Topic :: Scientific/Engineering :: Bio-Informatics
Requires-Python: >=3.8
License-File: LICENSE
Requires-Dist: pandas>=1.3.0
Requires-Dist: numpy>=1.20.0
Requires-Dist: matplotlib>=3.4.0
Requires-Dist: snakemake>=7.0.0
Requires-Dist: pyyaml>=5.0.0
Provides-Extra: viz
Requires-Dist: graphviz>=0.20.0; extra == "viz"
Provides-Extra: dev
Requires-Dist: pytest>=6.0; extra == "dev"
Requires-Dist: black; extra == "dev"
Requires-Dist: flake8; extra == "dev"
Requires-Dist: twine; extra == "dev"
Requires-Dist: build; extra == "dev"
Dynamic: license-file
